pyscms/__init__.py
pyscms/tools.py
pyscms-0.0.1.dist-info/LICENSE
pyscms-0.0.1.dist-info/METADATA
pyscms-0.0.1.dist-info/WHEEL
pyscms-0.0.1.dist-info/top_level.txt
pyscms-0.0.1.dist-info/RECORD
