Metadata-Version: 2.1
Name: pyscms
Version: 0.0.1
Summary: A package for single cell mass spectrometry data analysis
Author-email: yuanhy <yhy_9110@163.com>
Project-URL: Homepage, https://github.com/404563471/pyscms
Project-URL: Issues, https://github.com/404563471/pyscms/issues
Classifier: Programming Language :: Python :: 3
Classifier: License :: OSI Approved :: MIT License
Classifier: Operating System :: OS Independent
Requires-Python: >=3.8
License-File: LICENSE
